chartwerk/__init__.py
chartwerk/admin.py
chartwerk/apps.py
chartwerk/celery.py
chartwerk/conf.py
chartwerk/models.py
chartwerk/serializers.py
chartwerk/signals.py
chartwerk/tests.py
chartwerk/urls.py
chartwerk/views.py
chartwerk/fixtures/free_charts.json
chartwerk/fixtures/free_templates.json
chartwerk/migrations/0001_initial.py
chartwerk/migrations/0002_loadfreetemplates.py
chartwerk/migrations/0003_auto_20170601_1302.py
chartwerk/migrations/__init__.py
chartwerk/static/.DS_Store
chartwerk/static/chartwerk/.DS_Store
chartwerk/static/chartwerk/css/app.css
chartwerk/static/chartwerk/css/client.css
chartwerk/static/chartwerk/css/editor.css
chartwerk/static/chartwerk/css/main.css
chartwerk/static/chartwerk/css/reset.css
chartwerk/static/chartwerk/css/vendor.css
chartwerk/static/chartwerk/css/browse/styles.css
chartwerk/static/chartwerk/css/browse/styles.css.map
chartwerk/static/chartwerk/css/home/styles.css
chartwerk/static/chartwerk/css/home/styles.css.map
chartwerk/static/chartwerk/css/myWerk/styles.css
chartwerk/static/chartwerk/css/myWerk/styles.css.map
chartwerk/static/chartwerk/css/shared/styles.css
chartwerk/static/chartwerk/css/shared/styles.css.map
chartwerk/static/chartwerk/css/start/styles.css
chartwerk/static/chartwerk/css/start/styles.css.map
chartwerk/static/chartwerk/fonts/FontAwesome.otf
chartwerk/static/chartwerk/fonts/OpenSans.woff2
chartwerk/static/chartwerk/fonts/OpenSans.woff2.b64
chartwerk/static/chartwerk/fonts/fontawesome-webfont.eot
chartwerk/static/chartwerk/fonts/fontawesome-webfont.svg
chartwerk/static/chartwerk/fonts/fontawesome-webfont.ttf
chartwerk/static/chartwerk/fonts/fontawesome-webfont.woff
chartwerk/static/chartwerk/fonts/fontawesome-webfont.woff2
chartwerk/static/chartwerk/fonts/glyphicons-halflings-regular.eot
chartwerk/static/chartwerk/fonts/glyphicons-halflings-regular.svg
chartwerk/static/chartwerk/fonts/glyphicons-halflings-regular.ttf
django_chartwerk-0.5.19.dist-info/DESCRIPTION.rst
django_chartwerk-0.5.19.dist-info/METADATA
django_chartwerk-0.5.19.dist-info/RECORD
django_chartwerk-0.5.19.dist-info/WHEEL
django_chartwerk-0.5.19.dist-info/metadata.json
django_chartwerk-0.5.19.dist-info/top_level.txt
